CHANGELOG.md
MANIFEST.in
README.md
setup.py
Meneco.egg-info/PKG-INFO
Meneco.egg-info/SOURCES.txt
Meneco.egg-info/dependency_links.txt
Meneco.egg-info/entry_points.txt
Meneco.egg-info/requires.txt
Meneco.egg-info/top_level.txt
meneco/__init__.py
meneco/__main__.py
meneco/meneco.py
meneco/query.py
meneco/sbml.py
meneco/utils.py
meneco/encodings/card_min_completions_all_targets.lp
meneco/encodings/card_min_completions_all_targets_with_bounds.lp
meneco/encodings/completions_all_targets.lp
meneco/encodings/heuristic.lp
meneco/encodings/ireactions.lp
meneco/encodings/unproducible_targets.lp