Metadata-Version: 2.1
Name: Meneco
Version: 2.0.1
Summary: Metabolic Network Completion. Compute minimal completions to your draft network with reactions from a repair network.
Home-page: http://bioasp.github.io/meneco/
Author: Sven Thiele
Author-email: sthiele78@gmail.com
License: GPLv3+
Platform: UNKNOWN
